coffeepy/__init__.py
coffeepy/coffeepy.py
coffeepy-0.2.1.dist-info/LICENSE
coffeepy-0.2.1.dist-info/METADATA
coffeepy-0.2.1.dist-info/WHEEL
coffeepy-0.2.1.dist-info/entry_points.txt
coffeepy-0.2.1.dist-info/top_level.txt
coffeepy-0.2.1.dist-info/RECORD
