Metadata-Version: 2.1
Name: coffeepy
Version: 0.2.1
Summary: Coffeepy prevents the system from sleeping
Author-email: kuvaus <coffeepy@kuvaus.org>
Project-URL: Homepage, https://github.com/kuvaus/coffeepy
Project-URL: Bug Tracker, https://github.com/kuvaus/coffeepy/issues
Classifier: Operating System :: MacOS
Classifier: Operating System :: Microsoft :: Windows
Classifier: Operating System :: POSIX :: Linux
Classifier: Operating System :: OS Independent
Classifier: Programming Language :: Python :: 3
Classifier: Programming Language :: Python :: 3.7
Classifier: Programming Language :: Python :: 3.8
Classifier: Programming Language :: Python :: 3.9
Classifier: Programming Language :: Python :: 3.10
Classifier: Programming Language :: Python :: 3.11
Classifier: License :: OSI Approved :: MIT License
Requires-Python: >=3.7
License-File: LICENSE
Requires-Dist: jeepney ; sys_platform == "linux"
